scadnano/__init__.py
scadnano/modifications.py
scadnano/origami_rectangle.py
scadnano/scadnano.py
scadnano-0.20.1.dist-info/licenses/LICENSE.txt
scadnano-0.20.1.dist-info/METADATA
scadnano-0.20.1.dist-info/WHEEL
scadnano-0.20.1.dist-info/top_level.txt
scadnano-0.20.1.dist-info/RECORD
