Metadata-Version: 2.4
Name: scadnano
Version: 0.20.1
Summary: Python scripting library for generating designs readable by scadnano.
Home-page: https://github.com/UC-Davis-molecular-computing/scadnano-python-package
Download-URL: https://github.com/UC-Davis-molecular-computing/scadnano-python-package/archive/v0.20.1.zip
Author: David Doty
Author-email: doty@ucdavis.edu
License: MIT
Requires-Python: >=3.7
License-File: LICENSE.txt
Requires-Dist: openpyxl
Requires-Dist: tabulate
Dynamic: author
Dynamic: author-email
Dynamic: description
Dynamic: description-content-type
Dynamic: download-url
Dynamic: home-page
Dynamic: license
Dynamic: license-file
Dynamic: requires-dist
Dynamic: requires-python
Dynamic: summary
